cpair/__init__.py
cpair/cpair.py
cpair/point.py
cpair-1.0.0.dist-info/LICENSE
cpair-1.0.0.dist-info/WHEEL
cpair-1.0.0.dist-info/METADATA
cpair-1.0.0.dist-info/RECORD
